looker_validator/__init__.py
looker_validator/__main__.py
looker_validator/async_cli.py
looker_validator/async_client.py
looker_validator/branch_manager.py
looker_validator/config.py
looker_validator/diagnose.py
looker_validator/diagnose_sdk.py
looker_validator/exceptions.py
looker_validator/logger.py
looker_validator/looker_sdk_diagnostic.py
looker_validator/printer.py
looker_validator/result_model.py
looker_validator/utils/__init__.py
looker_validator/utils/helpers.py
looker_validator/validators/__init__.py
looker_validator/validators/assert_validator.py
looker_validator/validators/base_validator.py
looker_validator/validators/content_validator.py
looker_validator/validators/lookml_validator.py
looker_validator/validators/sql_validator.py
looker_validator/validators/wrapper_cli.py
looker_validator-0.4.0.dist-info/licenses/LICENSE
looker_validator-0.4.0.dist-info/METADATA
looker_validator-0.4.0.dist-info/WHEEL
looker_validator-0.4.0.dist-info/entry_points.txt
looker_validator-0.4.0.dist-info/top_level.txt
looker_validator-0.4.0.dist-info/RECORD
