Metadata-Version: 2.4
Name: looker-validator
Version: 0.4.0
Summary: A continuous integration tool for Looker and LookML validation
Home-page: https://github.com/stankovicst/looker-validator
Author: Stevan Stankovic
Author-email: stankovicst@mediamarktsaturn.com
Project-URL: Bug Tracker, https://github.com/stankovicst/looker-validator/issues
Project-URL: Documentation, https://github.com/stankovicst/looker-validator#readme
Project-URL: Source Code, https://github.com/stankovicst/looker-validator
Keywords: looker,lookml,validation,ci,continuous integration,testing
Classifier: Development Status :: 3 - Alpha
Classifier: Intended Audience :: Developers
Classifier: Topic :: Software Development :: Quality Assurance
Classifier: Programming Language :: Python :: 3
Classifier: Programming Language :: Python :: 3.8
Classifier: Programming Language :: Python :: 3.9
Classifier: Programming Language :: Python :: 3.10
Classifier: Programming Language :: Python :: 3.11
Classifier: License :: OSI Approved :: MIT License
Classifier: Operating System :: OS Independent
Requires-Python: >=3.8
License-File: LICENSE
Requires-Dist: looker-sdk==24.16.2
Requires-Dist: click>=8.0.0
Requires-Dist: pyyaml>=6.0
Requires-Dist: tqdm>=4.65.0
Requires-Dist: requests>=2.28.0
Requires-Dist: colorama>=0.4.6
Requires-Dist: backoff>=2.2.1
Requires-Dist: aiohttp>=3.9.1
Requires-Dist: aiocache>=0.12.2
Requires-Dist: httpx>=0.25.2
Requires-Dist: pydantic>=2.5.2
Requires-Dist: rich>=13.3.0
Provides-Extra: dev
Requires-Dist: pytest>=7.0.0; extra == "dev"
Requires-Dist: pytest-cov>=4.0.0; extra == "dev"
Requires-Dist: black>=23.0.0; extra == "dev"
Requires-Dist: flake8>=6.0.0; extra == "dev"
Requires-Dist: mypy>=1.0.0; extra == "dev"
Requires-Dist: build>=0.10.0; extra == "dev"
Requires-Dist: twine>=4.0.0; extra == "dev"
Dynamic: author
Dynamic: author-email
Dynamic: classifier
Dynamic: description
Dynamic: description-content-type
Dynamic: home-page
Dynamic: keywords
Dynamic: license-file
Dynamic: project-url
Dynamic: provides-extra
Dynamic: requires-dist
Dynamic: requires-python
Dynamic: summary
